PDielec/AbinitOutputReader.py
PDielec/Calculator.py
PDielec/CastepOutputReader.py
PDielec/Constants.py
PDielec/CrystalOutputReader.py
PDielec/DielectricFunction.py
PDielec/ExperimentOutputReader.py
PDielec/GTMcore.py
PDielec/GenericOutputReader.py
PDielec/GulpOutputReader.py
PDielec/HelperRoutines.py
PDielec/IO.py
PDielec/Materials.py
PDielec/MaterialsDataBase.xlsx
PDielec/Mie.py
PDielec/PhonopyOutputReader.py
PDielec/Plotter.py
PDielec/PrimitiveCell.py
PDielec/QEOutputReader.py
PDielec/SuperCell.py
PDielec/UnitCell.py
PDielec/Utilities.py
PDielec/VaspOutputReader.py
PDielec/__init__.py
PDielec/checkcsv.py
PDielec/checkexcel.py
PDielec/graphdatagenerator.py
PDielec/p1reader.py
PDielec/p2cif.py
PDielec/pdcompare.py
PDielec/pdgui.py
PDielec/pdmake.py
PDielec/phonopy_pdielec_born.py
PDielec/pickled_reader.py
PDielec/preader.py
PDielec/vibanalysis.py
PDielec/GUI/AnalysisTab.py
PDielec/GUI/App.py
PDielec/GUI/FitterTab.py
PDielec/GUI/MainTab.py
PDielec/GUI/NoteBook.py
PDielec/GUI/OpenGLWidget.py
PDielec/GUI/PlottingTab.py
PDielec/GUI/PowderScenarioTab.py
PDielec/GUI/ScenarioTab.py
PDielec/GUI/SettingsTab.py
PDielec/GUI/SingleCrystalLayer.py
PDielec/GUI/SingleCrystalScenarioTab.py
PDielec/GUI/SpreadSheetManager.py
PDielec/GUI/ViewerTab.py
PDielec/GUI/__init__.py
PDielec/GUI/splash.png
pdielec-9.0.1.dist-info/licenses/LICENSE.md
pdielec-9.0.1.dist-info/licenses/LICENSE.txt
pdielec-9.0.1.dist-info/METADATA
pdielec-9.0.1.dist-info/WHEEL
pdielec-9.0.1.dist-info/entry_points.txt
pdielec-9.0.1.dist-info/top_level.txt
pdielec-9.0.1.dist-info/RECORD
