Metadata-Version: 2.4
Name: pdielec
Version: 9.0.1
Summary: PDielec package for the calculation of THz and infrared spectra for powders and single crystals
Author-email: John Kendrick <john@kendrick.me.uk>, Andrew Burnett <A.D.Burnett@leeds.ac.uk>
Maintainer-email: John Kendrick <john@kendrick.me.uk>, Andrew Burnett <A.D.Burnett@leeds.ac.uk>
License: The MIT License (MIT)
Project-URL: Homepage, https://johnkendrick.github.io/PDielec
Project-URL: Documentation, https://johnkendrick.github.io/PDielec
Project-URL: Repository, https://github.com/JohnKendrick/PDielec.git
Project-URL: Bug Tracker, https://github.com/JohnKendrick/PDielec/issues
Project-URL: Changelog, https://github.com/JohnKendrick/PDielec/blob/master/CHANGES.txt
Keywords: Infrared, Infrared Spectroscopy,THz Spectroscopy,Terahertz Spectroscopy,Bruggeman,Maxwell-Garnett,Effective Medium,Phonon,Powder,Single Crystal
Classifier: Development Status :: 5 - Production/Stable
Classifier: Programming Language :: Python :: 3
Classifier: Programming Language :: Python :: 3.7
Classifier: Programming Language :: Python :: 3.8
Classifier: Programming Language :: Python :: 3.9
Classifier: Programming Language :: Python :: 3.10
Classifier: Programming Language :: Python :: 3.11
Classifier: Programming Language :: Python :: 3.12
Classifier: Operating System :: OS Independent
Requires-Python: >=3.7
License-File: LICENSE.md
License-File: LICENSE.txt
Requires-Dist: setuptools
Requires-Dist: scipy
Requires-Dist: numpy
Requires-Dist: matplotlib
Requires-Dist: openpyxl
Requires-Dist: psutil
Requires-Dist: PyOpenGL
Requires-Dist: PyQt6
Requires-Dist: QtPy
Requires-Dist: PyYAML
Requires-Dist: dill
Requires-Dist: scikit_learn
Requires-Dist: spglib
Requires-Dist: termcolor
Requires-Dist: XlsxWriter
Requires-Dist: openpyxl
Requires-Dist: imageio
Requires-Dist: imageio-ffmpeg
Dynamic: license-file
